<annotation>
	<folder>IMG_0823 (10-27-2020 11-52-36 PM)</folder>
	<filename>IMG_0823 0932.jpg</filename>
	<path>D:\Luan van\Frame\IMG_0823 (10-27-2020 11-52-36 PM)\IMG_0823 0932.jpg</path>
	<source>
		<database>Unknown</database>
	</source>
	<size>
		<width>1920</width>
		<height>1080</height>
		<depth>3</depth>
	</size>
	<segmented>0</segmented>
	<object>
		<name>vehicle</name>
		<pose>Unspecified</pose>
		<truncated>0</truncated>
		<difficult>0</difficult>
		<bndbox>
			<xmin>595</xmin>
			<ymin>607</ymin>
			<xmax>747</xmax>
			<ymax>765</ymax>
		</bndbox>
	</object>
	<object>
		<name>vehicle</name>
		<pose>Unspecified</pose>
		<truncated>0</truncated>
		<difficult>0</difficult>
		<bndbox>
			<xmin>745</xmin>
			<ymin>620</ymin>
			<xmax>1066</xmax>
			<ymax>751</ymax>
		</bndbox>
	</object>
	<object>
		<name>vehicle</name>
		<pose>Unspecified</pose>
		<truncated>0</truncated>
		<difficult>0</difficult>
		<bndbox>
			<xmin>339</xmin>
			<ymin>622</ymin>
			<xmax>633</xmax>
			<ymax>765</ymax>
		</bndbox>
	</object>
	<object>
		<name>vehicle</name>
		<pose>Unspecified</pose>
		<truncated>0</truncated>
		<difficult>0</difficult>
		<bndbox>
			<xmin>18</xmin>
			<ymin>588</ymin>
			<xmax>516</xmax>
			<ymax>1022</ymax>
		</bndbox>
	</object>
</annotation>
