<annotation>
	<folder>IMG_0823 (10-27-2020 11-52-36 PM)</folder>
	<filename>IMG_0823 0505.jpg</filename>
	<path>D:\Luan van\Frame\IMG_0823 (10-27-2020 11-52-36 PM)\IMG_0823 0505.jpg</path>
	<source>
		<database>Unknown</database>
	</source>
	<size>
		<width>1920</width>
		<height>1080</height>
		<depth>3</depth>
	</size>
	<segmented>0</segmented>
	<object>
		<name>vehicle</name>
		<pose>Unspecified</pose>
		<truncated>0</truncated>
		<difficult>0</difficult>
		<bndbox>
			<xmin>56</xmin>
			<ymin>530</ymin>
			<xmax>408</xmax>
			<ymax>938</ymax>
		</bndbox>
	</object>
	<object>
		<name>vehicle</name>
		<pose>Unspecified</pose>
		<truncated>0</truncated>
		<difficult>0</difficult>
		<bndbox>
			<xmin>1141</xmin>
			<ymin>541</ymin>
			<xmax>1580</xmax>
			<ymax>903</ymax>
		</bndbox>
	</object>
	<object>
		<name>vehicle</name>
		<pose>Unspecified</pose>
		<truncated>0</truncated>
		<difficult>0</difficult>
		<bndbox>
			<xmin>578</xmin>
			<ymin>576</ymin>
			<xmax>756</xmax>
			<ymax>765</ymax>
		</bndbox>
	</object>
	<object>
		<name>vehicle</name>
		<pose>Unspecified</pose>
		<truncated>0</truncated>
		<difficult>0</difficult>
		<bndbox>
			<xmin>418</xmin>
			<ymin>611</ymin>
			<xmax>574</xmax>
			<ymax>763</ymax>
		</bndbox>
	</object>
</annotation>
